NeoLang/__init__.py
NeoLang/main.py
NeoLang/interpreter/__init__.py
NeoLang/interpreter/operator.py
NeoLang/interpreter/parser.py
NeoLang/interpreter/tokenizer.py
NeoLang/syntax/__init__.py
NeoLang/syntax/package.py
NeoLang/syntax/parser.py
NeoLang/syntax/pipe.py
NeoLang/syntax/packages/Default/mathematics.py
NeoLang/syntax/packages/Default/package-info.json
NeoLang/syntax/packages/Default/todo.md
NeoLang/syntax/packages/Default/basic/input.py
NeoLang/syntax/packages/Default/basic/print.py
neolang-0.0.1.dist-info/LICENSE
neolang-0.0.1.dist-info/METADATA
neolang-0.0.1.dist-info/WHEEL
neolang-0.0.1.dist-info/entry_points.txt
neolang-0.0.1.dist-info/top_level.txt
neolang-0.0.1.dist-info/RECORD
